HSwindtunnel/__init__.py
HSwindtunnel/computeAirFlow.py
HSwindtunnel-1.0.0.dist-info/LICENSE.txt
HSwindtunnel-1.0.0.dist-info/METADATA
HSwindtunnel-1.0.0.dist-info/WHEEL
HSwindtunnel-1.0.0.dist-info/top_level.txt
HSwindtunnel-1.0.0.dist-info/RECORD
