Metadata-Version: 2.1
Name: HSwindtunnel
Version: 1.0.0
Summary: Package to compute the airflow through the HS wind tunnel
Home-page: https://github.com/jacobv95/HSwindtunnel
Download-URL: https://github.com/jacobv95/HSwindtunnel/archive/refs/tags/v1.0.tar.gz
Author: Jacob Vestergaard
Author-email: jacobvestergaard95@gmail.com
License: MIT
Keywords: HS wind tunnel
Classifier: Development Status :: 3 - Alpha
Classifier: Intended Audience :: Developers
Classifier: Topic :: Software Development :: Build Tools
Classifier: License :: OSI Approved :: MIT License
Classifier: Programming Language :: Python :: 3
Requires-Python: >=3.10
License-File: LICENSE.txt
Requires-Dist: pyees
